LICENSE
NOTICE
README.md
setup.cfg
setup.py
emr_notebooks_magics/__init__.py
emr_notebooks_magics/execute_emr_notebook.py
emr_notebooks_magics/generate_s3_presigned_url.py
emr_notebooks_magics/mount_workspace_dir.py
emr_notebooks_magics.egg-info/PKG-INFO
emr_notebooks_magics.egg-info/SOURCES.txt
emr_notebooks_magics.egg-info/dependency_links.txt
emr_notebooks_magics.egg-info/requires.txt
emr_notebooks_magics.egg-info/top_level.txt
emr_notebooks_magics/utils/__init__.py
emr_notebooks_magics/utils/display_utils.py
emr_notebooks_magics/utils/instance_metadata_service_utils.py
emr_notebooks_magics/utils/str_utils.py
startup_script/001-setup-emr-notebook-magics.py