Metadata-Version: 2.1
Name: emr-notebooks-magics
Version: 0.2.4
Summary: Jupyter Magics for EMR Notebooks.
Author-email: emrnotebooks@amazon.com
License: UNKNOWN
Platform: UNKNOWN
Classifier: Development Status :: 4 - Beta
Classifier: Intended Audience :: Developers
Classifier: Natural Language :: English
Classifier: License :: OSI Approved :: Apache Software License
License-File: LICENSE
License-File: NOTICE
